Workbook
Name qt_anos: GHE_IVEST!$D$24
Name Rendimento: GHE_IVEST!$D$19
Name Rendimento_carteira: GHE_IVEST!$D$19

Sheet GHE_IVEST
B17: CONFIGURAÇÕES
B18: Salário | D18: 2000
B19: Rendimento Carteira | D19: 0.006
B20: Sujestão de investimento (30%) | D20: =(D18*30%) -> 600
B22: Investimento Mensal
B23: Quanto vou invertir por mês ? | D23: 200
B24: Por Quantos Anos ? | D24: 5
B25: Taxa de Rendimento mensal ? | D25: 0.01079
B26: Patrimonio acumulado ? | D26: =FV(D25,D24*12,D23*-1) -> 16755.383
B27: Dividendos Mesais ? | D27: =D26*Rendimento -> 100.5323
B29: Cenários | D29: Dividendo
A30: 2 | B30: Quanto em 2 anos ? | C30: =FV($D$25,A30*12,$D$23*-1) -> 5445.5255 | D30: =(C30*Rendimento_carteira) -> 32.673153
A31: 5 | B31: Quanto em 5 anos ? | C31: =FV($D$25,A31*12,$D$23*-1) -> 16755.383 | D31: =(C31*Rendimento_carteira) -> 100.5323
A32: 10 | B32: Quanto em 10 anos ? | C32: =FV($D$25,A32*12,$D$23*-1) -> 48656.843 | D32: =(C32*Rendimento_carteira) -> 291.94106
A33: 20 | B33: Quanto em 20 anos ? | C33: =FV($D$25,A33*12,$D$23*-1) -> 225039.68 | D33: =(C33*Rendimento_carteira) -> 1350.2381
A34: 30 | B34: Quanto em 30 anos ? | C34: =FV($D$25,A34*12,$D$23*-1) -> 864433.93 | D34: =(C34*Rendimento_carteira) -> 5186.6036
B37: PERFIL | D37: AGRESSIVO
B38: VALOR A SER INVESTIDO POR MÊS | D38: =D23 -> 200
B40: TIPO DE FII | C40: PERCENTUAL SUGERIDO | D40: VALORES
B41: PAPEL | C41: =VLOOKUP($D$37&"-"&B41,Planilha2!A5:D22,4,) -> 0.5 | D41: =C41*$D$38 -> 100
B42: TIJOLO | C42: =VLOOKUP($D$37&"-"&B42,Planilha2!A6:D23,4,) -> 0.1 | D42: =C42*$D$38 -> 20
B43: HIBRIDOS | C43: =VLOOKUP($D$37&"-"&B43,Planilha2!A7:D24,4,) -> 0.05 | D43: =C43*$D$38 -> 10
B44: FOF'S | C44: =VLOOKUP($D$37&"-"&B44,Planilha2!A8:D25,4,) -> 0.05 | D44: =C44*$D$38 -> 10
B45: DESENVOLVIMENTO | C45: =VLOOKUP($D$37&"-"&B45,Planilha2!A9:D26,4,) -> 0.2 | D45: =C45*$D$38 -> 40
B46: HOTELARIA | C46: =VLOOKUP($D$37&"-"&B46,Planilha2!A10:D27,4,) -> 0.1 | D46: =C46*$D$38 -> 20
D47: =SUM(D41:D46) -> 200

Sheet Planilha2
A4: CHAVE | B4: PERFIES | C4: TIPO DE FII | D4: %
A5: =B5&"-"&C5 -> CONSERVADOR -PAPEL | B5: CONSERVADOR | C5: PAPEL | D5: 0.3 | I5: %
A6: =B6&"-"&C6 -> CONSERVADOR -TIJOLO | B6: CONSERVADOR | C6: TIJOLO | D6: 0.5 | G6: MODERADO-TIJOLO | I6: =VLOOKUP(G6,$A:$D,4,FALSE) -> 0.35
A7: =B7&"-"&C7 -> CONSERVADOR -HIBRIDOS | B7: CONSERVADOR | C7: HIBRIDOS | D7: 0.1
A8: =B8&"-"&C8 -> CONSERVADOR -FOF'S | B8: CONSERVADOR | C8: FOF'S | D8: 0.1
A9: =B9&"-"&C9 -> CONSERVADOR -DESENVOLVIMENTO | B9: CONSERVADOR | C9: DESENVOLVIMENTO | D9: 0
A10: =B10&"-"&C10 -> CONSERVADOR -HOTELARIA | B10: CONSERVADOR | C10: HOTELARIA | D10: 0
A11: =B11&"-"&C11 -> MODERADO-PAPEL | B11: MODERADO | C11: PAPEL | D11: 0.32
A12: =B12&"-"&C12 -> MODERADO-TIJOLO | B12: MODERADO | C12: TIJOLO | D12: 0.35
A13: =B13&"-"&C13 -> MODERADO-HIBRIDOS | B13: MODERADO | C13: HIBRIDOS | D13: 0.08
A14: =B14&"-"&C14 -> MODERADO-FOF'S | B14: MODERADO | C14: FOF'S | D14: 0.05
A15: =B15&"-"&C15 -> MODERADO-DESENVOLVIMENTO | B15: MODERADO | C15: DESENVOLVIMENTO | D15: 0.1
A16: =B16&"-"&C16 -> MODERADO-HOTELARIA | B16: MODERADO | C16: HOTELARIA | D16: 0.1
A17: =B17&"-"&C17 -> AGRESSIVO-PAPEL | B17: AGRESSIVO | C17: PAPEL | D17: 0.5
A18: =B18&"-"&C18 -> AGRESSIVO-TIJOLO | B18: AGRESSIVO | C18: TIJOLO | D18: 0.1
... A22: =B22&"-"&C22 -> AGRESSIVO-HOTELARIA | B22: AGRESSIVO | C22: HOTELARIA | D22: 0.1
